{
  "strategy_name": "FisherBBSolipsis",
  "params": {
    "roi": {
      "0": 100
    },
    "stoploss": {
      "stoploss": -0.99
    },
    "trailing": {
      "trailing_stop": true,
      "trailing_stop_positive": 0.24,
      "trailing_stop_positive_offset": 0.32799999999999996,
      "trailing_only_offset_is_reached": false
    },
    "buy": {
      "buy_bb_gain": 0.06,
      "buy_enable_signal_fisher_bb": true,
      "buy_enable_signal_fisher_hull": false,
      "buy_fisher": 0.63,
      "inf_pct_adr": 0.93,
      "xbtc_base_rmi": 43,
      "xbtc_guard": "none",
      "xtra_base_fiat_rmi": 39,
      "xtra_base_stake_rmi": 22
    },
    "sell": {
      "csell_endtrend_respect_roi": false,
      "csell_pullback": false,
      "csell_pullback_amount": 0.022,
      "csell_pullback_respect_roi": false,
      "csell_roi_end": 0.003,
      "csell_roi_start": 0.022,
      "csell_roi_time": 904,
      "csell_roi_type": "step",
      "csell_trend_type": "candle",
      "cstop_bail_how": "time",
      "cstop_bail_roc": -3.273,
      "cstop_bail_time": 382,
      "cstop_bail_time_trend": false,
      "cstop_loss_threshold": -0.048
    },
    "protection": {}
  },
  "ft_stratparam_v": 1,
  "export_time": "2021-12-18 05:12:20.401664+00:00"
}