{
  "strategy_name": "FisherBBWtdProfit",
  "params": {
    "stoploss": {
      "stoploss": -0.1
    },
    "trailing": {
      "trailing_stop": true,
      "trailing_stop_positive": 0.01,
      "trailing_stop_positive_offset": 0.043,
      "trailing_only_offset_is_reached": true
    },
    "buy": {
      "buy_bb_gain": 0.074,
      "buy_fisher": 0.968,
      "buy_num_candles": 0
    },
    "sell": {},
    "protection": {},
    "roi": {
      "0": 0.135,
      "36": 0.098,
      "73": 0.028,
      "175": 0
    }
  },
  "ft_stratparam_v": 1,
  "export_time": "2022-01-06 03:29:22.946829+00:00"
}