{
  "strategy_name": "FisherBBWtdProfit",
  "params": {
    "roi": {
      "0": 0.042,
      "3": 0.038,
      "14": 0.013,
      "38": 0
    },
    "stoploss": {
      "stoploss": -0.1
    },
    "buy": {
      "buy_bb_gain": 0.073,
      "buy_fisher": -0.741,
      "buy_num_candles": 1
    },
    "sell": {},
    "protection": {},
    "trailing": {
      "trailing_stop": true,
      "trailing_stop_positive": 0.01,
      "trailing_stop_positive_offset": 0.033,
      "trailing_only_offset_is_reached": true
    }
  },
  "ft_stratparam_v": 1,
  "export_time": "2021-12-26 22:40:54.779655+00:00"
}