{
  "strategy_name": "Anomaly_dwt",
  "params": {
    "roi": {
      "0": 0.06
    },
    "stoploss": {
      "stoploss": -0.99
    },
    "trailing": {
      "trailing_stop": false,
      "trailing_stop_positive": null,
      "trailing_stop_positive_offset": 0.0,
      "trailing_only_offset_is_reached": false
    },
    "max_open_trades": {
      "max_open_trades": 3
    },
    "buy": {},
    "sell": {
      "cexit_endtrend_respect_roi": true,
      "cexit_pullback": false,
      "cexit_pullback_amount": 0.014,
      "cexit_pullback_respect_roi": true,
      "cexit_roi_end": 0.006,
      "cexit_roi_start": 0.03,
      "cexit_roi_time": 1412,
      "cexit_roi_type": "decay",
      "cexit_trend_type": "none",
      "cstop_bail_how": "roc",
      "cstop_bail_roc": -1.602,
      "cstop_bail_time": 200,
      "cstop_bail_time_trend": false,
      "cstop_loss_threshold": -0.011,
      "cstop_max_stoploss": -0.244,
      "pHSL": -0.043,
      "pPF_1": 0.01,
      "pPF_2": 0.066,
      "pSL_1": 0.008,
      "pSL_2": 0.038
    },
    "protection": {}
  },
  "ft_stratparam_v": 1,
  "export_time": "2023-03-28 05:57:21.994957+00:00"
}