{
  "strategy_name": "FFT_2",
  "params": {
    "roi": {
      "0": 10
    },
    "stoploss": {
      "stoploss": -0.1
    },
    "trailing": {
      "trailing_stop": false,
      "trailing_stop_positive": null,
      "trailing_stop_positive_offset": 0.0,
      "trailing_only_offset_is_reached": false
    },
    "buy": {
      "buy_fft_gain": 0.02,
      "buy_fft_predict": 2
    },
    "sell": {
      "sell_fft_loss": -0.004
    },
    "protection": {}
  },
  "ft_stratparam_v": 1,
  "export_time": "2022-03-02 01:13:22.993653+00:00"
}