{
  "strategy_name": "FBB_DWT2",
  "params": {
    "roi": {
      "0": 0.1
    },
    "stoploss": {
      "stoploss": -0.1
    },
    "trailing": {
      "trailing_stop": false,
      "trailing_stop_positive": null,
      "trailing_stop_positive_offset": 0.0,
      "trailing_only_offset_is_reached": false
    },
    "buy": {
      "buy_bb_gain": 0.05,
      "buy_dwt_diff": 0.06,
      "buy_fisher_wr": -0.97,
      "buy_force_fisher_wr": -0.98
    },
    "sell": {
      "csell_endtrend_respect_roi": true,
      "csell_pullback": true,
      "csell_pullback_amount": 0.01,
      "csell_pullback_respect_roi": true,
      "csell_roi_end": 0.009,
      "csell_roi_start": 0.014,
      "csell_roi_time": 1140,
      "csell_roi_type": "static",
      "csell_trend_type": "none",
      "cstop_bail_how": "any",
      "cstop_bail_roc": -2.199,
      "cstop_bail_time": 996,
      "cstop_bail_time_trend": false,
      "cstop_loss_threshold": -0.049,
      "cstop_max_stoploss": -0.046,
      "sell_bb_gain": 1.2,
      "sell_dwt_diff": -0.6,
      "sell_fisher_wr": 0.85,
      "sell_force_fisher_wr": 0.87
    },
    "protection": {}
  },
  "ft_stratparam_v": 1,
  "export_time": "2022-04-05 23:31:22.124468+00:00"
}