{
  "strategy_name": "TS_Wavelet_FFTA",
  "params": {
    "roi": {
      "0": 0.04,
      "100": 0.02
    },
    "stoploss": {
      "stoploss": -0.1
    },
    "trailing": {
      "trailing_stop": false,
      "trailing_stop_positive": null,
      "trailing_stop_positive_offset": 0.0,
      "trailing_only_offset_is_reached": false
    },
    "max_open_trades": {
      "max_open_trades": 5
    },
    "buy": {
      "cexit_min_profit_th": 0.3,
      "cexit_profit_nstd": 1.9,
      "enable_bb_check": false,
      "enable_guard_metric": true,
      "enable_squeeze": false,
      "entry_bb_factor": 0.82,
      "entry_bb_width": 0.025,
      "entry_guard_metric": -0.3
    },
    "sell": {
      "cexit_loss_nstd": 1.8,
      "cexit_metric_overbought": 0.76,
      "cexit_metric_take_profit": 0.94,
      "cexit_min_loss_th": -1.4,
      "enable_exit_signal": true,
      "exit_bb_factor": 1.01,
      "exit_guard_metric": 0.7
    },
    "protection": {}
  },
  "ft_stratparam_v": 1,
  "export_time": "2024-02-09 18:27:57.113011+00:00"
}